[
  {
    "id": "15466",
    "modality": "personal",
    "creditor": "Claudette Morel",
    "date": "2024-05-01T20:35:16.253Z",
    "creditValue": 4200,
    "status": "rejected"
  },
  {
    "id": "54566",
    "modality": "auto",
    "creditor": "David King",
    "date": "2024-04-07T20:35:16.253Z",
    "creditValue": 2000,
    "status": "approved"
  },
  {
    "id": "46444",
    "modality": "mortgage",
    "creditor": "The Trapper",
    "date": "2024-08-07T20:35:16.253Z",
    "creditValue": 8000,
    "status": "pending"
  }
]
